setup.py
audiocalc/__init__.py
audiocalc/_audiocalc.pyx
audiocalc/benchmark_damping.py
audiocalc/example01.py
audiocalc/py_audiocalc.py
audiocalc/test.py
audiocalc.egg-info/PKG-INFO
audiocalc.egg-info/SOURCES.txt
audiocalc.egg-info/dependency_links.txt
audiocalc.egg-info/top_level.txt