Metadata-Version: 1.0
Name: audiocalc
Version: 0.0.9
Summary: A few audio/sound calculation utilities
Home-page: https://github.com/marians/audiocalc
Author: Marian Steinbach
Author-email: marian@sendung.de
License: MIT
Platform: UNKNOWN
